stygian_compressor/__init__.py
stygian_compressor/py.typed
stygian_compressor/version.py
stygian_compressor-1.0.0.dist-info/licenses/LICENSE.txt
stygian_compressor-1.0.0.dist-info/METADATA
stygian_compressor-1.0.0.dist-info/WHEEL
stygian_compressor-1.0.0.dist-info/top_level.txt
stygian_compressor-1.0.0.dist-info/RECORD
