Metadata-Version: 2.4
Name: stygian_compressor
Version: 1.0.0
Summary: LZMA compression for stygian
Author-email: Suprock Technologies <inquiries@suprocktech.com>
License-Expression: ISC
Project-URL: Repository, https://bitbucket.org/suprocktech/stygian_compressor
Keywords: asphodel,suprock,apd
Classifier: Topic :: System :: Hardware
Requires-Python: >=3.10
License-File: LICENSE.txt
Dynamic: license-file
